geneorder/__init__.py
geneorder/_modidx.py
geneorder/core.py
geneorder/util.py
geneorder-0.0.5.dist-info/licenses/LICENSE
geneorder-0.0.5.dist-info/METADATA
geneorder-0.0.5.dist-info/WHEEL
geneorder-0.0.5.dist-info/entry_points.txt
geneorder-0.0.5.dist-info/top_level.txt
geneorder-0.0.5.dist-info/RECORD
